git_commit_generator/__init__.py
git_commit_generator/config.py
git_commit_generator/core.py
git_commit_generator/validators.py
git_quick_auto-0.1.0.dist-info/licenses/LICENSE
git_quick_auto-0.1.0.dist-info/METADATA
git_quick_auto-0.1.0.dist-info/WHEEL
git_quick_auto-0.1.0.dist-info/entry_points.txt
git_quick_auto-0.1.0.dist-info/top_level.txt
git_quick_auto-0.1.0.dist-info/RECORD
