Metadata-Version: 2.4
Name: git_quick-auto
Version: 0.1.0
Summary: 基于AI的Git提交信息生成工具，帮助开发者快速生成规范的提交信息
Author-email: xiaoming <xiaomindexiaomin@126.com>
License: MIT
Project-URL: Homepage, https://github.com/axiaomina123/git-commit-generator
Project-URL: Bug Tracker, https://github.com/axiaomina123/git-commit-generator/issues
Classifier: Programming Language :: Python :: 3
Classifier: License :: OSI Approved :: MIT License
Classifier: Operating System :: OS Independent
Classifier: Topic :: Software Development :: Version Control :: Git
Classifier: Intended Audience :: Developers
Requires-Python: >=3.10
License-File: LICENSE
Requires-Dist: gitpython>=3.1
Requires-Dist: questionary>=2.1.0
Requires-Dist: requests>=2.25
Requires-Dist: typer>=0.15.2
Requires-Dist: rich>=13.0.0
Requires-Dist: click>=8.0.0
Dynamic: license-file
